<annotation>
	<folder>image</folder>
	<filename>E0000632.jpg</filename>
	<path>Y:\Eden_Eye_Balls\image\E0000632.jpg</path>
	<source>
		<database>Unknown</database>
	</source>
	<size>
		<width>1289</width>
		<height>1920</height>
		<depth>3</depth>
	</size>
	<segmented>0</segmented>
	<object>
		<name>0</name>
		<pose>Unspecified</pose>
		<truncated>0</truncated>
		<difficult>0</difficult>
		<bndbox>
			<xmin>574</xmin>
			<ymin>338</ymin>
			<xmax>599</xmax>
			<ymax>360</ymax>
		</bndbox>
	</object>
	<object>
		<name>0</name>
		<pose>Unspecified</pose>
		<truncated>0</truncated>
		<difficult>0</difficult>
		<bndbox>
			<xmin>677</xmin>
			<ymin>372</ymin>
			<xmax>699</xmax>
			<ymax>388</ymax>
		</bndbox>
	</object>
</annotation>
