<annotation>
	<folder>image</folder>
	<filename>E0002468.jpg</filename>
	<path>Z:\Eden_Eye_Balls\image\E0002468.jpg</path>
	<source>
		<database>Unknown</database>
	</source>
	<size>
		<width>1285</width>
		<height>1920</height>
		<depth>3</depth>
	</size>
	<segmented>0</segmented>
	<object>
		<name>0</name>
		<pose>Unspecified</pose>
		<truncated>0</truncated>
		<difficult>0</difficult>
		<bndbox>
			<xmin>352</xmin>
			<ymin>456</ymin>
			<xmax>390</xmax>
			<ymax>481</ymax>
		</bndbox>
	</object>
	<object>
		<name>0</name>
		<pose>Unspecified</pose>
		<truncated>0</truncated>
		<difficult>0</difficult>
		<bndbox>
			<xmin>534</xmin>
			<ymin>418</ymin>
			<xmax>570</xmax>
			<ymax>447</ymax>
		</bndbox>
	</object>
</annotation>
