<annotation>
	<folder>image</folder>
	<filename>E0001933.jpg</filename>
	<path>Y:\Eden_Eye_Balls\image\E0001933.jpg</path>
	<source>
		<database>Unknown</database>
	</source>
	<size>
		<width>1920</width>
		<height>1278</height>
		<depth>3</depth>
	</size>
	<segmented>0</segmented>
	<object>
		<name>0</name>
		<pose>Unspecified</pose>
		<truncated>0</truncated>
		<difficult>0</difficult>
		<bndbox>
			<xmin>1351</xmin>
			<ymin>397</ymin>
			<xmax>1373</xmax>
			<ymax>421</ymax>
		</bndbox>
	</object>
	<object>
		<name>0</name>
		<pose>Unspecified</pose>
		<truncated>0</truncated>
		<difficult>0</difficult>
		<bndbox>
			<xmin>1473</xmin>
			<ymin>389</ymin>
			<xmax>1501</xmax>
			<ymax>411</ymax>
		</bndbox>
	</object>
</annotation>
